medical_mcps/__init__.py
medical_mcps/http_server.py
medical_mcps/med_mcp_server.py
medical_mcps/sentry_config.py
medical_mcps/settings.py
medical_mcps/stdio_server.py
medical_mcps/api_clients/__init__.py
medical_mcps/api_clients/base_client.py
medical_mcps/api_clients/biolink_helpers.py
medical_mcps/api_clients/chembl_client.py
medical_mcps/api_clients/ctg_client.py
medical_mcps/api_clients/cypher_builder.py
medical_mcps/api_clients/gwas_client.py
medical_mcps/api_clients/kegg_client.py
medical_mcps/api_clients/metapaths.py
medical_mcps/api_clients/mychem_client.py
medical_mcps/api_clients/mydisease_client.py
medical_mcps/api_clients/mygene_client.py
medical_mcps/api_clients/myvariant_client.py
medical_mcps/api_clients/nci_client.py
medical_mcps/api_clients/neo4j_client.py
medical_mcps/api_clients/nodenorm_client.py
medical_mcps/api_clients/omim_client.py
medical_mcps/api_clients/openfda_client.py
medical_mcps/api_clients/opentargets_client.py
medical_mcps/api_clients/pathwaycommons_client.py
medical_mcps/api_clients/pubmed_client.py
medical_mcps/api_clients/reactome_client.py
medical_mcps/api_clients/uniprot_client.py
medical_mcps/models/__init__.py
medical_mcps/models/base.py
medical_mcps/models/biothings.py
medical_mcps/models/chembl.py
medical_mcps/models/ctg.py
medical_mcps/models/gwas.py
medical_mcps/models/myvariant.py
medical_mcps/models/nci.py
medical_mcps/models/nodenorm.py
medical_mcps/models/omim.py
medical_mcps/models/openfda.py
medical_mcps/models/opentargets.py
medical_mcps/models/pathwaycommons.py
medical_mcps/models/pubmed.py
medical_mcps/models/reactome.py
medical_mcps/models/uniprot.py
medical_mcps/servers/__init__.py
medical_mcps/servers/biothings_server.py
medical_mcps/servers/chembl_server.py
medical_mcps/servers/ctg_server.py
medical_mcps/servers/gwas_server.py
medical_mcps/servers/kegg_server.py
medical_mcps/servers/myvariant_server.py
medical_mcps/servers/nci_server.py
medical_mcps/servers/neo4j_helpers.py
iflow_mcp_pascalwhoop_medical_mcps-0.1.16.dist-info/METADATA
iflow_mcp_pascalwhoop_medical_mcps-0.1.16.dist-info/WHEEL
iflow_mcp_pascalwhoop_medical_mcps-0.1.16.dist-info/entry_points.txt
iflow_mcp_pascalwhoop_medical_mcps-0.1.16.dist-info/licenses/LICENSE
iflow_mcp_pascalwhoop_medical_mcps-0.1.16.dist-info/RECORD
