Metadata-Version: 2.4
Name: iflow-mcp_pascalwhoop_medical-mcps
Version: 0.1.16
Summary: MCP servers for biological and medical APIs
Project-URL: Homepage, https://github.com/pascalwhoop/medical-mcps
Project-URL: Documentation, https://github.com/pascalwhoop/medical-mcps#readme
Project-URL: Repository, https://github.com/pascalwhoop/medical-mcps
Project-URL: Issues, https://github.com/pascalwhoop/medical-mcps/issues
Author-email: Pascal Brokmeier <git@pascalbrokmeier.de>
License: MIT License
License-File: LICENSE
Keywords: api,bioinformatics,biology,chembl,kegg,mcp,medical,pubmed,reactome,uniprot
Classifier: Development Status :: 4 - Beta
Classifier: Intended Audience :: Developers
Classifier: Intended Audience :: Healthcare Industry
Classifier: Intended Audience :: Science/Research
Classifier: License :: OSI Approved :: MIT License
Classifier: Programming Language :: Python :: 3
Classifier: Programming Language :: Python :: 3.12
Classifier: Topic :: Scientific/Engineering :: Bio-Informatics
Classifier: Topic :: Scientific/Engineering :: Medical Science Apps.
Requires-Python: >=3.12
Requires-Dist: bmt>=0.7.0
Requires-Dist: chembl-webresource-client>=0.10.9
Requires-Dist: hishel[httpx,requests]>=1.1.5
Requires-Dist: httpx[http2]>=0.27.0
Requires-Dist: mcp>=1.0.0
Requires-Dist: neo4j>=5.0.0
Requires-Dist: pydantic-settings>=2.0.0
Requires-Dist: pydantic>=2.0.0
Requires-Dist: pyyaml>=6.0.0
Requires-Dist: requests>=2.31.0
Requires-Dist: sentry-sdk[mcp]>=2.44.0
Requires-Dist: starlette>=0.49.0
Requires-Dist: tenacity>=8.2.0
Requires-Dist: uvicorn[standard]>=0.30.0
